geolime_rs/__init__.py
geolime_rs-1.0.0.dist-info/licenses/LICENSE
geolime_rs-1.0.0.dist-info/METADATA
geolime_rs-1.0.0.dist-info/WHEEL
geolime_rs-1.0.0.dist-info/top_level.txt
geolime_rs-1.0.0.dist-info/RECORD
