Metadata-Version: 2.4
Name: geolime_rs
Version: 1.0.0
Summary: GeoLime_rs is part of GeoLime ecosystem
Author-email: DeepLime <contact@deeplime.io>
Project-URL: Homepage, https://github.com/deeplime-io/geolime_rs-pypi-package
Project-URL: Repository, https://github.com/deeplime-io/geolime_rs-pypi-package
Keywords: geolime_rs,geolime,geostats
Classifier: Programming Language :: Python :: 3
Classifier: Operating System :: OS Independent
Requires-Python: >=3.8
License-File: LICENSE
Dynamic: license-file
